custom_settings/__init__.py
custom_settings/adapters.py
custom_settings/exc.py
custom_settings/loaders.py
custom_settings/utils.py
custom_settings/tests/__init__.py
custom_settings/tests/compat.py
custom_settings/tests/settings.py
custom_settings/tests/test_adapters.py
custom_settings/tests/test_loaders.py
custom_settings/tests/test_utils.py
custom_settings-1.0.post1.dist-info/DESCRIPTION.rst
custom_settings-1.0.post1.dist-info/METADATA
custom_settings-1.0.post1.dist-info/RECORD
custom_settings-1.0.post1.dist-info/WHEEL
custom_settings-1.0.post1.dist-info/entry_points.txt
custom_settings-1.0.post1.dist-info/metadata.json
custom_settings-1.0.post1.dist-info/top_level.txt
