Metadata-Version: 2.0
Name: custom-settings
Version: 1.0.post1
Summary: Utility for the settings file
Home-page: https://github.com/TakesxiSximada/custom_settings
Author: TakesxiSximada
Author-email: sximada+custom_settings@gmail.com
License: Apache License 2.0
Keywords: Settings,Django
Platform: any
Classifier: Development Status :: 5 - Production/Stable
Classifier: License :: OSI Approved :: Apache Software License
Classifier: Programming Language :: Python
Classifier: Programming Language :: Python :: 2
Classifier: Programming Language :: Python :: 2.7
Classifier: Programming Language :: Python :: 3
Classifier: Programming Language :: Python :: 3.4
Classifier: Programming Language :: Python :: 3.5
Classifier: Topic :: Software Development
Requires-Dist: six
Requires-Dist: zope.dottedname
Provides-Extra: testing
Requires-Dist: detox; extra == 'testing'
Requires-Dist: flake8; extra == 'testing'
Requires-Dist: mock; extra == 'testing'
Requires-Dist: pytest; extra == 'testing'
Requires-Dist: pytest-cov; extra == 'testing'
Requires-Dist: pytest-flake8; extra == 'testing'
Requires-Dist: pytest-xdist; extra == 'testing'
Requires-Dist: pytz; extra == 'testing'
Requires-Dist: six; extra == 'testing'
Requires-Dist: zope.dottedname; extra == 'testing'
